pennylane_qiskit/__init__.py
pennylane_qiskit/_version.py
pennylane_qiskit/aer.py
pennylane_qiskit/basic_sim.py
pennylane_qiskit/converter.py
pennylane_qiskit/noise_models.py
pennylane_qiskit/qiskit_device.py
pennylane_qiskit/qiskit_device_legacy.py
pennylane_qiskit/remote.py
pennylane_qiskit-0.42.0.dist-info/licenses/LICENSE
pennylane_qiskit-0.42.0.dist-info/METADATA
pennylane_qiskit-0.42.0.dist-info/WHEEL
pennylane_qiskit-0.42.0.dist-info/entry_points.txt
pennylane_qiskit-0.42.0.dist-info/top_level.txt
pennylane_qiskit-0.42.0.dist-info/RECORD
