Metadata-Version: 2.4
Name: PennyLane-qiskit
Version: 0.42.0
Summary: PennyLane plugin for Qiskit
Home-page: https://github.com/XanaduAI/pennylane-qiskit
Maintainer: Xanadu
Maintainer-email: software@xanadu.ai
License: Apache License 2.0
Classifier: Development Status :: 4 - Beta
Classifier: Environment :: Console
Classifier: Intended Audience :: Science/Research
Classifier: License :: OSI Approved :: Apache Software License
Classifier: Natural Language :: English
Classifier: Operating System :: POSIX
Classifier: Operating System :: MacOS :: MacOS X
Classifier: Operating System :: POSIX :: Linux
Classifier: Operating System :: Microsoft :: Windows
Classifier: Programming Language :: Python
Classifier: Programming Language :: Python :: 3
Classifier: Programming Language :: Python :: 3.10
Classifier: Programming Language :: Python :: 3.11
Classifier: Programming Language :: Python :: 3.12
Classifier: Programming Language :: Python :: 3 :: Only
Classifier: Topic :: Scientific/Engineering :: Physics
Provides: pennylane_qiskit
License-File: LICENSE
Requires-Dist: qiskit<1.3,>=0.32
Requires-Dist: qiskit-aer<0.16.1
Requires-Dist: qiskit-ibm-runtime<=0.29
Requires-Dist: pennylane>=0.42
Requires-Dist: numpy
Requires-Dist: sympy<1.13
Requires-Dist: networkx>=2.2
Dynamic: classifier
Dynamic: description
Dynamic: home-page
Dynamic: license
Dynamic: license-file
Dynamic: maintainer
Dynamic: maintainer-email
Dynamic: provides
Dynamic: requires-dist
Dynamic: summary
